{"number": "SB2416", "url": "https://capitol.texas.gov/BillLookup/History.aspx?LegSess=89R&Bill=SB2416", "caption": "Relating to a preference against state resources being used to compete against private commercial sources.", "authors": "Hagenbuch", "last_action": "03/12/2025 S Filed", "summary": "<br>This bill amends Texas Government Code to establish purchasing preferences for goods and services. While not directly targeting Chinese immigrants, it creates a tiered preference system favoring Texas and US products over foreign products. This could indirectly impact Chinese-owned businesses or imports from China when competing for Texas state contracts.<br>", "translation": "<br>\u8be5\u6cd5\u6848\u4fee\u6539\u5fb7\u514b\u8428\u65af\u5dde\u653f\u5e9c\u6cd5\u89c4\uff0c\u5efa\u7acb\u5546\u54c1\u548c\u670d\u52a1\u91c7\u8d2d\u7684\u4f18\u5148\u987a\u5e8f\u5236\u5ea6\u3002\u867d\u7136\u6ca1\u6709\u76f4\u63a5\u9488\u5bf9\u4e2d\u56fd\u79fb\u6c11\uff0c\u4f46\u5b83\u5efa\u7acb\u4e86\u4e00\u4e2a\u4f18\u5148\u8003\u8651\u5fb7\u514b\u8428\u65af\u5dde\u548c\u7f8e\u56fd\u4ea7\u54c1\u800c\u975e\u5916\u56fd\u4ea7\u54c1\u7684\u5206\u7ea7\u5236\u5ea6\u3002\u8fd9\u53ef\u80fd\u95f4\u63a5\u5f71\u54cd\u5230\u5728\u7ade\u4e89\u5fb7\u514b\u8428\u65af\u5dde\u653f\u5e9c\u5408\u540c\u65f6\u7684\u4e2d\u8d44\u4f01\u4e1a\u6216\u6765\u81ea\u4e2d\u56fd\u7684\u8fdb\u53e3\u4ea7\u54c1\u3002<br>", "committees": "<br>1. State Affairs Committee<br>2. Government Operations Committee<br>3. Economic Development Committee<br>", "category": "Contracting and Investment"}